basicsec_mcp/__init__.py
basicsec_mcp/server.py
basicsec_mcp-1.0.0.dist-info/METADATA
basicsec_mcp-1.0.0.dist-info/WHEEL
basicsec_mcp-1.0.0.dist-info/entry_points.txt
basicsec_mcp-1.0.0.dist-info/top_level.txt
basicsec_mcp-1.0.0.dist-info/RECORD
