Metadata-Version: 2.4
Name: basicsec-mcp
Version: 1.0.0
Summary: Model Context Protocol server for DNS and email security scanning using basicsec
Home-page: https://github.com/marlinkcyber/basicsec-mcp
Author: Vlatko Kosturjak
Author-email: Vlatko Kosturjak <vlatko.kosturjak@marlink.com>
License: MIT
Project-URL: Homepage, https://github.com/marlinkcyber/basicsec-mcp
Project-URL: Bug Reports, https://github.com/marlinkcyber/basicsec-mcp/issues
Project-URL: Source, https://github.com/marlinkcyber/basicsec-mcp
Project-URL: Documentation, https://basicsec-mcp.readthedocs.io/
Classifier: Development Status :: 4 - Beta
Classifier: Intended Audience :: Developers
Classifier: Intended Audience :: System Administrators
Classifier: Topic :: Security
Classifier: Topic :: Internet :: Name Service (DNS)
Classifier: Topic :: Communications :: Email
Classifier: License :: OSI Approved :: MIT License
Classifier: Programming Language :: Python :: 3
Classifier: Programming Language :: Python :: 3.8
Classifier: Programming Language :: Python :: 3.9
Classifier: Programming Language :: Python :: 3.10
Classifier: Programming Language :: Python :: 3.11
Classifier: Programming Language :: Python :: 3.12
Requires-Python: >=3.8
Requires-Dist: basicsec>=1.0.0
Requires-Dist: mcp>=1.0.0
Provides-Extra: dev
Requires-Dist: pytest>=7.0.0; extra == "dev"
Requires-Dist: pytest-cov>=4.0.0; extra == "dev"
Requires-Dist: black>=23.0.0; extra == "dev"
Requires-Dist: flake8>=6.0.0; extra == "dev"
Requires-Dist: mypy>=1.0.0; extra == "dev"
Dynamic: author
Dynamic: home-page
Dynamic: requires-python
